[
  {
    "from": "Blue Whale",
    "to": "Snail"
  },
  {
    "from": "Blue Whale",
    "to": "Alligator"
  },
  {
    "from": "Blue Whale",
    "to": "Lark"
  },
  {
    "from": "Blue Whale",
    "to": "Fruit Bat"
  },
  {
    "from": "Blue Whale",
    "to": "Gerbil"
  },
  {
    "from": "Blue Whale",
    "to": "Hyena"
  },
  {
    "from": "Lark",
    "to": "Alligator"
  },
  {
    "from": "Lark",
    "to": "Starfish"
  },
  {
    "from": "Lark",
    "to": "Carp"
  },
  {
    "from": "Lark",
    "to": "Bee"
  },
  {
    "from": "Lark",
    "to": "Giraffe"
  },
  {
    "from": "Lark",
    "to": "Asp"
  },
  {
    "from": "Carp",
    "to": "Domestic Canary"
  },
  {
    "from": "Carp",
    "to": "Buffalo"
  },
  {
    "from": "Carp",
    "to": "Star-Nosed Mole"
  },
  {
    "from": "Carp",
    "to": "Arctic Wolf"
  },
  {
    "from": "Carp",
    "to": "Porcupine"
  },
  {
    "from": "Domestic Canary",
    "to": "Alligator"
  },
  {
    "from": "Domestic Canary",
    "to": "Fruit Bat"
  },
  {
    "from": "Domestic Canary",
    "to": "Bee"
  },
  {
    "from": "Domestic Canary",
    "to": "Reindeer"
  },
  {
    "from": "Domestic Canary",
    "to": "Muskox"
  },
  {
    "from": "Domestic Canary",
    "to": "Leopard"
  },
  {
    "from": "Armadillo",
    "to": "Crane Fly"
  },
  {
    "from": "Armadillo",
    "to": "Carp"
  },
  {
    "from": "Armadillo",
    "to": "Emu"
  },
  {
    "from": "Armadillo",
    "to": "Badger"
  },
  {
    "from": "Armadillo",
    "to": "Takin"
  },
  {
    "from": "Buffalo",
    "to": "Emu"
  },
  {
    "from": "Buffalo",
    "to": "Bee"
  },
  {
    "from": "Buffalo",
    "to": "Domestic Canary"
  },
  {
    "from": "Buffalo",
    "to": "Carp"
  },
  {
    "from": "Buffalo",
    "to": "Heron"
  },
  {
    "from": "Buffalo",
    "to": "Basilisk"
  },
  {
    "from": "Fruit Bat",
    "to": "Penguin"
  },
  {
    "from": "Fruit Bat",
    "to": "Lark"
  },
  {
    "from": "Fruit Bat",
    "to": "Domestic Canary"
  },
  {
    "from": "Fruit Bat",
    "to": "Beetle"
  },
  {
    "from": "Fruit Bat",
    "to": "Amphibian"
  },
  {
    "from": "Rhinoceros",
    "to": "Domestic Canary"
  },
  {
    "from": "Rhinoceros",
    "to": "Snail"
  },
  {
    "from": "Rhinoceros",
    "to": "Carp"
  },
  {
    "from": "Rhinoceros",
    "to": "Armadillo"
  },
  {
    "from": "Rhinoceros",
    "to": "Bonobo"
  },
  {
    "from": "Rhinoceros",
    "to": "Jellyfish"
  },
  {
    "from": "Fowl",
    "to": "Starfish"
  },
  {
    "from": "Fowl",
    "to": "Emu"
  },
  {
    "from": "Fowl",
    "to": "Donkey"
  },
  {
    "from": "Fowl",
    "to": "Rhinoceros"
  },
  {
    "from": "Fowl",
    "to": "Arabian Leopard"
  },
  {
    "from": "Fowl",
    "to": "Lemur"
  },
  {
    "from": "Crane Fly",
    "to": "Penguin"
  },
  {
    "from": "Crane Fly",
    "to": "Fowl"
  },
  {
    "from": "Crane Fly",
    "to": "Bee"
  },
  {
    "from": "Crane Fly",
    "to": "Swift"
  },
  {
    "from": "Crane Fly",
    "to": "Aphid"
  },
  {
    "from": "Reindeer",
    "to": "Lark"
  },
  {
    "from": "Reindeer",
    "to": "Donkey"
  },
  {
    "from": "Reindeer",
    "to": "Penguin"
  },
  {
    "from": "Reindeer",
    "to": "Fowl"
  },
  {
    "from": "Reindeer",
    "to": "Heron"
  },
  {
    "from": "Reindeer",
    "to": "Arctic Wolf"
  },
  {
    "from": "Penguin",
    "to": "Blue Whale"
  },
  {
    "from": "Penguin",
    "to": "Star-Nosed Mole"
  },
  {
    "from": "Penguin",
    "to": "Lark"
  },
  {
    "from": "Penguin",
    "to": "Fruit Bat"
  },
  {
    "from": "Penguin",
    "to": "Locust"
  },
  {
    "from": "Penguin",
    "to": "Peafowl"
  },
  {
    "from": "Emu",
    "to": "Alligator"
  },
  {
    "from": "Emu",
    "to": "Reindeer"
  },
  {
    "from": "Emu",
    "to": "Buffalo"
  },
  {
    "from": "Emu",
    "to": "Donkey"
  },
  {
    "from": "Emu",
    "to": "Heron"
  },
  {
    "from": "Emu",
    "to": "Whale"
  },
  {
    "from": "Bee",
    "to": "Fruit Bat"
  },
  {
    "from": "Bee",
    "to": "Rhinoceros"
  },
  {
    "from": "Bee",
    "to": "Snail"
  },
  {
    "from": "Bee",
    "to": "Starfish"
  },
  {
    "from": "Bee",
    "to": "Bald Eagle"
  },
  {
    "from": "Bee",
    "to": "Woodpecker"
  },
  {
    "from": "Alligator",
    "to": "Bee"
  },
  {
    "from": "Alligator",
    "to": "Reindeer"
  },
  {
    "from": "Alligator",
    "to": "Carp"
  },
  {
    "from": "Alligator",
    "to": "Blue Whale"
  },
  {
    "from": "Alligator",
    "to": "Minnow"
  },
  {
    "from": "Alligator",
    "to": "Alpaca"
  },
  {
    "from": "Star-Nosed Mole",
    "to": "Bee"
  },
  {
    "from": "Star-Nosed Mole",
    "to": "Domestic Canary"
  },
  {
    "from": "Star-Nosed Mole",
    "to": "Alligator"
  },
  {
    "from": "Star-Nosed Mole",
    "to": "Raven"
  },
  {
    "from": "Star-Nosed Mole",
    "to": "Crocodile"
  },
  {
    "from": "Star-Nosed Mole",
    "to": "Muskox"
  },
  {
    "from": "Starfish",
    "to": "Emu"
  },
  {
    "from": "Starfish",
    "to": "Donkey"
  },
  {
    "from": "Starfish",
    "to": "Fowl"
  },
  {
    "from": "Starfish",
    "to": "Crane Fly"
  },
  {
    "from": "Starfish",
    "to": "Bat"
  },
  {
    "from": "Starfish",
    "to": "Jay"
  },
  {
    "from": "Snail",
    "to": "Rhinoceros"
  },
  {
    "from": "Snail",
    "to": "Domestic Canary"
  },
  {
    "from": "Snail",
    "to": "Carp"
  },
  {
    "from": "Snail",
    "to": "Raven"
  },
  {
    "from": "Snail",
    "to": "Albatross"
  },
  {
    "from": "Snail",
    "to": "Badger"
  },
  {
    "from": "Donkey",
    "to": "Carp"
  },
  {
    "from": "Donkey",
    "to": "Reindeer"
  },
  {
    "from": "Donkey",
    "to": "Armadillo"
  },
  {
    "from": "Donkey",
    "to": "Blue Whale"
  },
  {
    "from": "Donkey",
    "to": "Possum"
  },
  {
    "from": "Donkey",
    "to": "Ape"
  },
  {
    "from": "Raven",
    "to": "Fowl"
  },
  {
    "from": "Raven",
    "to": "Alligator"
  },
  {
    "from": "Raven",
    "to": "Starfish"
  },
  {
    "from": "Raven",
    "to": "Reindeer"
  },
  {
    "from": "Raven",
    "to": "Mosquito"
  },
  {
    "from": "Raven",
    "to": "Albatross"
  },
  {
    "from": "Robin",
    "to": "Armadillo"
  },
  {
    "from": "Robin",
    "to": "Rhinoceros"
  },
  {
    "from": "Robin",
    "to": "Lark"
  },
  {
    "from": "Robin",
    "to": "Snail"
  },
  {
    "from": "Robin",
    "to": "Bat"
  },
  {
    "from": "Robin",
    "to": "Vicuna"
  },
  {
    "from": "Bonobo",
    "to": "Carp"
  },
  {
    "from": "Bonobo",
    "to": "Domestic Canary"
  },
  {
    "from": "Bonobo",
    "to": "Starfish"
  },
  {
    "from": "Bonobo",
    "to": "Reindeer"
  },
  {
    "from": "Bonobo",
    "to": "Elephant"
  },
  {
    "from": "Bonobo",
    "to": "Woodpecker"
  },
  {
    "from": "Harrier",
    "to": "Armadillo"
  },
  {
    "from": "Harrier",
    "to": "Emu"
  },
  {
    "from": "Harrier",
    "to": "Blue Whale"
  },
  {
    "from": "Harrier",
    "to": "Carp"
  },
  {
    "from": "Harrier",
    "to": "Falcon"
  },
  {
    "from": "Harrier",
    "to": "Mite"
  },
  {
    "from": "Swan",
    "to": "Blue Whale"
  },
  {
    "from": "Swan",
    "to": "Domestic Canary"
  },
  {
    "from": "Swan",
    "to": "Lark"
  },
  {
    "from": "Swan",
    "to": "Crane Fly"
  },
  {
    "from": "Swan",
    "to": "Anglerfish"
  },
  {
    "from": "Swan",
    "to": "Anteater"
  },
  {
    "from": "Takin",
    "to": "Domestic Canary"
  },
  {
    "from": "Takin",
    "to": "Bee"
  },
  {
    "from": "Takin",
    "to": "Crane Fly"
  },
  {
    "from": "Takin",
    "to": "Alligator"
  },
  {
    "from": "Takin",
    "to": "Donkey"
  },
  {
    "from": "Takin",
    "to": "Arrow Crab"
  },
  {
    "from": "Anglerfish",
    "to": "Rhinoceros"
  },
  {
    "from": "Anglerfish",
    "to": "Emu"
  },
  {
    "from": "Anglerfish",
    "to": "Reindeer"
  },
  {
    "from": "Anglerfish",
    "to": "Alligator"
  },
  {
    "from": "Anglerfish",
    "to": "Arctic Fox"
  },
  {
    "from": "Anglerfish",
    "to": "Ape"
  },
  {
    "from": "Beetle",
    "to": "Crane Fly"
  },
  {
    "from": "Beetle",
    "to": "Fruit Bat"
  },
  {
    "from": "Beetle",
    "to": "Fowl"
  },
  {
    "from": "Beetle",
    "to": "Bee"
  },
  {
    "from": "Beetle",
    "to": "Sheep"
  },
  {
    "from": "Beetle",
    "to": "Jellyfish"
  },
  {
    "from": "Hyena",
    "to": "Donkey"
  },
  {
    "from": "Hyena",
    "to": "Crane Fly"
  },
  {
    "from": "Hyena",
    "to": "Star-Nosed Mole"
  },
  {
    "from": "Hyena",
    "to": "Carp"
  },
  {
    "from": "Hyena",
    "to": "Arabian Leopard"
  },
  {
    "from": "Hyena",
    "to": "Mosquito"
  },
  {
    "from": "Woodpecker",
    "to": "Raven"
  },
  {
    "from": "Woodpecker",
    "to": "Reindeer"
  },
  {
    "from": "Woodpecker",
    "to": "Starfish"
  },
  {
    "from": "Woodpecker",
    "to": "Fruit Bat"
  },
  {
    "from": "Woodpecker",
    "to": "Ant"
  },
  {
    "from": "Woodpecker",
    "to": "Ground Shark"
  },
  {
    "from": "Badger",
    "to": "Starfish"
  },
  {
    "from": "Badger",
    "to": "Penguin"
  },
  {
    "from": "Badger",
    "to": "Reindeer"
  },
  {
    "from": "Badger",
    "to": "Armadillo"
  },
  {
    "from": "Badger",
    "to": "Turtle"
  },
  {
    "from": "Badger",
    "to": "Aardvark"
  },
  {
    "from": "Squirrel",
    "to": "Alligator"
  },
  {
    "from": "Squirrel",
    "to": "Carp"
  },
  {
    "from": "Squirrel",
    "to": "Reindeer"
  },
  {
    "from": "Squirrel",
    "to": "Blue Whale"
  },
  {
    "from": "Squirrel",
    "to": "Bison"
  },
  {
    "from": "Squirrel",
    "to": "Aardvark"
  },
  {
    "from": "Heron",
    "to": "Snail"
  },
  {
    "from": "Heron",
    "to": "Reindeer"
  },
  {
    "from": "Heron",
    "to": "Emu"
  },
  {
    "from": "Heron",
    "to": "Blue Whale"
  },
  {
    "from": "Heron",
    "to": "Arctic Wolf"
  },
  {
    "from": "Heron",
    "to": "Meadowlark"
  },
  {
    "from": "Alpaca",
    "to": "Donkey"
  },
  {
    "from": "Alpaca",
    "to": "Reindeer"
  },
  {
    "from": "Alpaca",
    "to": "Carp"
  },
  {
    "from": "Alpaca",
    "to": "Starfish"
  },
  {
    "from": "Alpaca",
    "to": "Bonobo"
  },
  {
    "from": "Alpaca",
    "to": "Bald Eagle"
  },
  {
    "from": "Ground Shark",
    "to": "Buffalo"
  },
  {
    "from": "Ground Shark",
    "to": "Armadillo"
  },
  {
    "from": "Ground Shark",
    "to": "Fruit Bat"
  },
  {
    "from": "Ground Shark",
    "to": "Raven"
  },
  {
    "from": "Ground Shark",
    "to": "Turtle"
  },
  {
    "from": "Ground Shark",
    "to": "Ant"
  },
  {
    "from": "Bat",
    "to": "Fruit Bat"
  },
  {
    "from": "Bat",
    "to": "Fowl"
  },
  {
    "from": "Bat",
    "to": "Blue Whale"
  },
  {
    "from": "Bat",
    "to": "Penguin"
  },
  {
    "from": "Bat",
    "to": "Peafowl"
  },
  {
    "from": "Bat",
    "to": "Robin"
  },
  {
    "from": "Mite",
    "to": "Alligator"
  },
  {
    "from": "Mite",
    "to": "Starfish"
  },
  {
    "from": "Mite",
    "to": "Blue Whale"
  },
  {
    "from": "Mite",
    "to": "Reindeer"
  },
  {
    "from": "Mite",
    "to": "Ocelot"
  },
  {
    "from": "Mite",
    "to": "Anglerfish"
  },
  {
    "from": "Ground Sloth",
    "to": "Snail"
  },
  {
    "from": "Ground Sloth",
    "to": "Starfish"
  },
  {
    "from": "Ground Sloth",
    "to": "Alligator"
  },
  {
    "from": "Ground Sloth",
    "to": "Bee"
  },
  {
    "from": "Ground Sloth",
    "to": "Leopard"
  },
  {
    "from": "Ground Sloth",
    "to": "Beetle"
  },
  {
    "from": "Ant",
    "to": "Alligator"
  },
  {
    "from": "Ant",
    "to": "Raven"
  },
  {
    "from": "Ant",
    "to": "Buffalo"
  },
  {
    "from": "Ant",
    "to": "Fowl"
  },
  {
    "from": "Ant",
    "to": "Arabian Leopard"
  },
  {
    "from": "Ant",
    "to": "Bat"
  },
  {
    "from": "Aardvark",
    "to": "Domestic Canary"
  },
  {
    "from": "Aardvark",
    "to": "Carp"
  },
  {
    "from": "Aardvark",
    "to": "Donkey"
  },
  {
    "from": "Aardvark",
    "to": "Alligator"
  },
  {
    "from": "Aardvark",
    "to": "Ape"
  },
  {
    "from": "Aardvark",
    "to": "Muskox"
  },
  {
    "from": "Baboon",
    "to": "Reindeer"
  },
  {
    "from": "Baboon",
    "to": "Donkey"
  },
  {
    "from": "Baboon",
    "to": "Fruit Bat"
  },
  {
    "from": "Baboon",
    "to": "Raven"
  },
  {
    "from": "Baboon",
    "to": "Anaconda"
  },
  {
    "from": "Baboon",
    "to": "Grouse"
  },
  {
    "from": "Aardwolf",
    "to": "Crane Fly"
  },
  {
    "from": "Aardwolf",
    "to": "Buffalo"
  },
  {
    "from": "Aardwolf",
    "to": "Armadillo"
  },
  {
    "from": "Aardwolf",
    "to": "Donkey"
  },
  {
    "from": "Aardwolf",
    "to": "Bat"
  },
  {
    "from": "Aardwolf",
    "to": "Guan"
  },
  {
    "from": "Vicuna",
    "to": "Snail"
  },
  {
    "from": "Vicuna",
    "to": "Fowl"
  },
  {
    "from": "Vicuna",
    "to": "Rhinoceros"
  },
  {
    "from": "Vicuna",
    "to": "Reindeer"
  },
  {
    "from": "Vicuna",
    "to": "Giraffe"
  },
  {
    "from": "Vicuna",
    "to": "Crocodile"
  },
  {
    "from": "Whale",
    "to": "Snail"
  },
  {
    "from": "Whale",
    "to": "Raven"
  },
  {
    "from": "Whale",
    "to": "Rhinoceros"
  },
  {
    "from": "Whale",
    "to": "Starfish"
  },
  {
    "from": "Whale",
    "to": "Possum"
  },
  {
    "from": "Whale",
    "to": "Jay"
  },
  {
    "from": "Albatross",
    "to": "Armadillo"
  },
  {
    "from": "Albatross",
    "to": "Snail"
  },
  {
    "from": "Albatross",
    "to": "Blue Whale"
  },
  {
    "from": "Albatross",
    "to": "Donkey"
  },
  {
    "from": "Albatross",
    "to": "Mite"
  },
  {
    "from": "Albatross",
    "to": "Baboon"
  },
  {
    "from": "Turtle",
    "to": "Rhinoceros"
  },
  {
    "from": "Turtle",
    "to": "Snail"
  },
  {
    "from": "Turtle",
    "to": "Alligator"
  },
  {
    "from": "Turtle",
    "to": "Blue Whale"
  },
  {
    "from": "Turtle",
    "to": "Bald Eagle"
  },
  {
    "from": "Turtle",
    "to": "Alpaca"
  },
  {
    "from": "Gerbil",
    "to": "Armadillo"
  },
  {
    "from": "Gerbil",
    "to": "Rhinoceros"
  },
  {
    "from": "Gerbil",
    "to": "Crane Fly"
  },
  {
    "from": "Gerbil",
    "to": "Starfish"
  },
  {
    "from": "Gerbil",
    "to": "Harrier"
  },
  {
    "from": "Gerbil",
    "to": "Woodpecker"
  },
  {
    "from": "Sheep",
    "to": "Fowl"
  },
  {
    "from": "Sheep",
    "to": "Blue Whale"
  },
  {
    "from": "Sheep",
    "to": "Lark"
  },
  {
    "from": "Sheep",
    "to": "Starfish"
  },
  {
    "from": "Sheep",
    "to": "Mosquito"
  },
  {
    "from": "Sheep",
    "to": "Alpaca"
  },
  {
    "from": "Ant",
    "to": "Blue Whale"
  },
  {
    "from": "Ant",
    "to": "Alligator"
  },
  {
    "from": "Ant",
    "to": "Bee"
  },
  {
    "from": "Ant",
    "to": "Penguin"
  },
  {
    "from": "Ant",
    "to": "Panda"
  },
  {
    "from": "Ant",
    "to": "Arrow Crab"
  },
  {
    "from": "Locust",
    "to": "Emu"
  },
  {
    "from": "Locust",
    "to": "Snail"
  },
  {
    "from": "Locust",
    "to": "Buffalo"
  },
  {
    "from": "Locust",
    "to": "Blue Whale"
  },
  {
    "from": "Locust",
    "to": "Dung Beetle"
  },
  {
    "from": "Locust",
    "to": "Woodpecker"
  },
  {
    "from": "Scale Insect",
    "to": "Fowl"
  },
  {
    "from": "Scale Insect",
    "to": "Star-Nosed Mole"
  },
  {
    "from": "Scale Insect",
    "to": "Donkey"
  },
  {
    "from": "Scale Insect",
    "to": "Penguin"
  },
  {
    "from": "Scale Insect",
    "to": "Anglerfish"
  },
  {
    "from": "Scale Insect",
    "to": "Amphibian"
  },
  {
    "from": "Arrow Crab",
    "to": "Raven"
  },
  {
    "from": "Arrow Crab",
    "to": "Crane Fly"
  },
  {
    "from": "Arrow Crab",
    "to": "Blue Whale"
  },
  {
    "from": "Arrow Crab",
    "to": "Star-Nosed Mole"
  },
  {
    "from": "Arrow Crab",
    "to": "Heron"
  },
  {
    "from": "Arrow Crab",
    "to": "Ape"
  },
  {
    "from": "Reptile",
    "to": "Alligator"
  },
  {
    "from": "Reptile",
    "to": "Bee"
  },
  {
    "from": "Reptile",
    "to": "Domestic Canary"
  },
  {
    "from": "Reptile",
    "to": "Fruit Bat"
  },
  {
    "from": "Reptile",
    "to": "Minnow"
  },
  {
    "from": "Reptile",
    "to": "Amphibian"
  },
  {
    "from": "Antlion",
    "to": "Bee"
  },
  {
    "from": "Antlion",
    "to": "Domestic Canary"
  },
  {
    "from": "Antlion",
    "to": "Armadillo"
  },
  {
    "from": "Antlion",
    "to": "Raven"
  },
  {
    "from": "Antlion",
    "to": "Asp"
  },
  {
    "from": "Antlion",
    "to": "Swan"
  },
  {
    "from": "Antelope",
    "to": "Emu"
  },
  {
    "from": "Antelope",
    "to": "Bee"
  },
  {
    "from": "Antelope",
    "to": "Snail"
  },
  {
    "from": "Antelope",
    "to": "Domestic Canary"
  },
  {
    "from": "Antelope",
    "to": "Albatross"
  },
  {
    "from": "Antelope",
    "to": "Ground Sloth"
  },
  {
    "from": "Lemur",
    "to": "Alligator"
  },
  {
    "from": "Lemur",
    "to": "Domestic Canary"
  },
  {
    "from": "Lemur",
    "to": "Carp"
  },
  {
    "from": "Lemur",
    "to": "Fruit Bat"
  },
  {
    "from": "Lemur",
    "to": "Giant Squid"
  },
  {
    "from": "Lemur",
    "to": "Arrow Crab"
  },
  {
    "from": "Arctic Fox",
    "to": "Bee"
  },
  {
    "from": "Arctic Fox",
    "to": "Donkey"
  },
  {
    "from": "Arctic Fox",
    "to": "Blue Whale"
  },
  {
    "from": "Arctic Fox",
    "to": "Domestic Canary"
  },
  {
    "from": "Arctic Fox",
    "to": "Anglerfish"
  },
  {
    "from": "Arctic Fox",
    "to": "Vicuna"
  },
  {
    "from": "Rook",
    "to": "Emu"
  },
  {
    "from": "Rook",
    "to": "Raven"
  },
  {
    "from": "Rook",
    "to": "Lark"
  },
  {
    "from": "Rook",
    "to": "Starfish"
  },
  {
    "from": "Rook",
    "to": "Squirrel"
  },
  {
    "from": "Rook",
    "to": "Arctic Wolf"
  },
  {
    "from": "Dingo",
    "to": "Rhinoceros"
  },
  {
    "from": "Dingo",
    "to": "Buffalo"
  },
  {
    "from": "Dingo",
    "to": "Bee"
  },
  {
    "from": "Dingo",
    "to": "Alligator"
  },
  {
    "from": "Dingo",
    "to": "Leopard"
  },
  {
    "from": "Dingo",
    "to": "Antlion"
  },
  {
    "from": "Elephant",
    "to": "Domestic Canary"
  },
  {
    "from": "Elephant",
    "to": "Fowl"
  },
  {
    "from": "Elephant",
    "to": "Carp"
  },
  {
    "from": "Elephant",
    "to": "Bee"
  },
  {
    "from": "Elephant",
    "to": "Dung Beetle"
  },
  {
    "from": "Elephant",
    "to": "Crocodile"
  },
  {
    "from": "Giant Squid",
    "to": "Reindeer"
  },
  {
    "from": "Giant Squid",
    "to": "Carp"
  },
  {
    "from": "Giant Squid",
    "to": "Buffalo"
  },
  {
    "from": "Giant Squid",
    "to": "Fruit Bat"
  },
  {
    "from": "Giant Squid",
    "to": "Jay"
  },
  {
    "from": "Giant Squid",
    "to": "Leopard"
  },
  {
    "from": "Salmon",
    "to": "Armadillo"
  },
  {
    "from": "Salmon",
    "to": "Donkey"
  },
  {
    "from": "Salmon",
    "to": "Penguin"
  },
  {
    "from": "Salmon",
    "to": "Emu"
  },
  {
    "from": "Salmon",
    "to": "Woodpecker"
  },
  {
    "from": "Salmon",
    "to": "Scale Insect"
  },
  {
    "from": "Amphibian",
    "to": "Blue Whale"
  },
  {
    "from": "Amphibian",
    "to": "Star-Nosed Mole"
  },
  {
    "from": "Amphibian",
    "to": "Starfish"
  },
  {
    "from": "Amphibian",
    "to": "Fowl"
  },
  {
    "from": "Amphibian",
    "to": "Aphid"
  },
  {
    "from": "Amphibian",
    "to": "Swift"
  },
  {
    "from": "Meadowlark",
    "to": "Reindeer"
  },
  {
    "from": "Meadowlark",
    "to": "Raven"
  },
  {
    "from": "Meadowlark",
    "to": "Carp"
  },
  {
    "from": "Meadowlark",
    "to": "Blue Whale"
  },
  {
    "from": "Meadowlark",
    "to": "Swift"
  },
  {
    "from": "Meadowlark",
    "to": "Ape"
  },
  {
    "from": "Guan",
    "to": "Crane Fly"
  },
  {
    "from": "Guan",
    "to": "Penguin"
  },
  {
    "from": "Guan",
    "to": "Star-Nosed Mole"
  },
  {
    "from": "Guan",
    "to": "Carp"
  },
  {
    "from": "Guan",
    "to": "Arctic Fox"
  },
  {
    "from": "Guan",
    "to": "Whale"
  },
  {
    "from": "Asp",
    "to": "Domestic Canary"
  },
  {
    "from": "Asp",
    "to": "Fruit Bat"
  },
  {
    "from": "Asp",
    "to": "Fowl"
  },
  {
    "from": "Asp",
    "to": "Snail"
  },
  {
    "from": "Asp",
    "to": "Turtle"
  },
  {
    "from": "Asp",
    "to": "Bat"
  },
  {
    "from": "Domestic Goose",
    "to": "Rhinoceros"
  },
  {
    "from": "Domestic Goose",
    "to": "Domestic Canary"
  },
  {
    "from": "Domestic Goose",
    "to": "Armadillo"
  },
  {
    "from": "Domestic Goose",
    "to": "Crane Fly"
  },
  {
    "from": "Domestic Goose",
    "to": "Takin"
  },
  {
    "from": "Domestic Goose",
    "to": "Badger"
  },
  {
    "from": "Jellyfish",
    "to": "Crane Fly"
  },
  {
    "from": "Jellyfish",
    "to": "Fowl"
  },
  {
    "from": "Jellyfish",
    "to": "Bee"
  },
  {
    "from": "Jellyfish",
    "to": "Donkey"
  },
  {
    "from": "Jellyfish",
    "to": "Arabian Leopard"
  },
  {
    "from": "Jellyfish",
    "to": "Mosquito"
  },
  {
    "from": "Possum",
    "to": "Lark"
  },
  {
    "from": "Possum",
    "to": "Fruit Bat"
  },
  {
    "from": "Possum",
    "to": "Crane Fly"
  },
  {
    "from": "Possum",
    "to": "Domestic Canary"
  },
  {
    "from": "Possum",
    "to": "Mite"
  },
  {
    "from": "Possum",
    "to": "Elephant"
  },
  {
    "from": "Bald Eagle",
    "to": "Alligator"
  },
  {
    "from": "Bald Eagle",
    "to": "Crane Fly"
  },
  {
    "from": "Bald Eagle",
    "to": "Star-Nosed Mole"
  },
  {
    "from": "Bald Eagle",
    "to": "Blue Whale"
  },
  {
    "from": "Bald Eagle",
    "to": "Arabian Leopard"
  },
  {
    "from": "Bald Eagle",
    "to": "Leopard"
  },
  {
    "from": "Crocodile",
    "to": "Star-Nosed Mole"
  },
  {
    "from": "Crocodile",
    "to": "Domestic Canary"
  },
  {
    "from": "Crocodile",
    "to": "Starfish"
  },
  {
    "from": "Crocodile",
    "to": "Raven"
  },
  {
    "from": "Crocodile",
    "to": "Swan"
  },
  {
    "from": "Crocodile",
    "to": "Ape"
  },
  {
    "from": "Donkey",
    "to": "Blue Whale"
  },
  {
    "from": "Donkey",
    "to": "Alligator"
  },
  {
    "from": "Donkey",
    "to": "Buffalo"
  },
  {
    "from": "Donkey",
    "to": "Penguin"
  },
  {
    "from": "Donkey",
    "to": "Sheep"
  },
  {
    "from": "Donkey",
    "to": "Locust"
  },
  {
    "from": "Jay",
    "to": "Starfish"
  },
  {
    "from": "Jay",
    "to": "Emu"
  },
  {
    "from": "Jay",
    "to": "Donkey"
  },
  {
    "from": "Jay",
    "to": "Buffalo"
  },
  {
    "from": "Jay",
    "to": "Basilisk"
  },
  {
    "from": "Jay",
    "to": "Whale"
  },
  {
    "from": "Cicada",
    "to": "Emu"
  },
  {
    "from": "Cicada",
    "to": "Crane Fly"
  },
  {
    "from": "Cicada",
    "to": "Reindeer"
  },
  {
    "from": "Cicada",
    "to": "Bee"
  },
  {
    "from": "Cicada",
    "to": "Arctic Wolf"
  },
  {
    "from": "Cicada",
    "to": "Antlion"
  },
  {
    "from": "Muskox",
    "to": "Reindeer"
  },
  {
    "from": "Muskox",
    "to": "Star-Nosed Mole"
  },
  {
    "from": "Muskox",
    "to": "Alligator"
  },
  {
    "from": "Muskox",
    "to": "Emu"
  },
  {
    "from": "Muskox",
    "to": "Ground Sloth"
  },
  {
    "from": "Muskox",
    "to": "Grouse"
  },
  {
    "from": "Arctic Wolf",
    "to": "Buffalo"
  },
  {
    "from": "Arctic Wolf",
    "to": "Emu"
  },
  {
    "from": "Arctic Wolf",
    "to": "Carp"
  },
  {
    "from": "Arctic Wolf",
    "to": "Alligator"
  },
  {
    "from": "Arctic Wolf",
    "to": "Angelfish"
  },
  {
    "from": "Arctic Wolf",
    "to": "Takin"
  },
  {
    "from": "Aphid",
    "to": "Fowl"
  },
  {
    "from": "Aphid",
    "to": "Snail"
  },
  {
    "from": "Aphid",
    "to": "Carp"
  },
  {
    "from": "Aphid",
    "to": "Donkey"
  },
  {
    "from": "Aphid",
    "to": "Alpaca"
  },
  {
    "from": "Aphid",
    "to": "Grouse"
  },
  {
    "from": "Bison",
    "to": "Starfish"
  },
  {
    "from": "Bison",
    "to": "Crane Fly"
  },
  {
    "from": "Bison",
    "to": "Star-Nosed Mole"
  },
  {
    "from": "Bison",
    "to": "Lark"
  },
  {
    "from": "Bison",
    "to": "Crocodile"
  },
  {
    "from": "Bison",
    "to": "Basilisk"
  },
  {
    "from": "Arabian Leopard",
    "to": "Domestic Canary"
  },
  {
    "from": "Arabian Leopard",
    "to": "Snail"
  },
  {
    "from": "Arabian Leopard",
    "to": "Emu"
  },
  {
    "from": "Arabian Leopard",
    "to": "Carp"
  },
  {
    "from": "Arabian Leopard",
    "to": "Ground Shark"
  },
  {
    "from": "Arabian Leopard",
    "to": "Heron"
  },
  {
    "from": "Basilisk",
    "to": "Domestic Canary"
  },
  {
    "from": "Basilisk",
    "to": "Rhinoceros"
  },
  {
    "from": "Basilisk",
    "to": "Carp"
  },
  {
    "from": "Basilisk",
    "to": "Lark"
  },
  {
    "from": "Basilisk",
    "to": "Swift"
  },
  {
    "from": "Basilisk",
    "to": "Salmon"
  },
  {
    "from": "Grouse",
    "to": "Armadillo"
  },
  {
    "from": "Grouse",
    "to": "Star-Nosed Mole"
  },
  {
    "from": "Grouse",
    "to": "Snail"
  },
  {
    "from": "Grouse",
    "to": "Alligator"
  },
  {
    "from": "Grouse",
    "to": "Beetle"
  },
  {
    "from": "Grouse",
    "to": "Aardwolf"
  },
  {
    "from": "Ape",
    "to": "Starfish"
  },
  {
    "from": "Ape",
    "to": "Emu"
  },
  {
    "from": "Ape",
    "to": "Raven"
  },
  {
    "from": "Ape",
    "to": "Crane Fly"
  },
  {
    "from": "Ape",
    "to": "Angelfish"
  },
  {
    "from": "Ape",
    "to": "Ground Sloth"
  },
  {
    "from": "Peafowl",
    "to": "Crane Fly"
  },
  {
    "from": "Peafowl",
    "to": "Carp"
  },
  {
    "from": "Peafowl",
    "to": "Bee"
  },
  {
    "from": "Peafowl",
    "to": "Fowl"
  },
  {
    "from": "Peafowl",
    "to": "Cicada"
  },
  {
    "from": "Peafowl",
    "to": "Mite"
  },
  {
    "from": "Ocelot",
    "to": "Domestic Canary"
  },
  {
    "from": "Ocelot",
    "to": "Penguin"
  },
  {
    "from": "Ocelot",
    "to": "Bee"
  },
  {
    "from": "Ocelot",
    "to": "Fruit Bat"
  },
  {
    "from": "Ocelot",
    "to": "Robin"
  },
  {
    "from": "Ocelot",
    "to": "Domestic Goose"
  },
  {
    "from": "Leopard",
    "to": "Raven"
  },
  {
    "from": "Leopard",
    "to": "Rhinoceros"
  },
  {
    "from": "Leopard",
    "to": "Blue Whale"
  },
  {
    "from": "Leopard",
    "to": "Bee"
  },
  {
    "from": "Leopard",
    "to": "Muskox"
  },
  {
    "from": "Leopard",
    "to": "Ground Shark"
  },
  {
    "from": "Giraffe",
    "to": "Domestic Canary"
  },
  {
    "from": "Giraffe",
    "to": "Alligator"
  },
  {
    "from": "Giraffe",
    "to": "Fruit Bat"
  },
  {
    "from": "Giraffe",
    "to": "Carp"
  },
  {
    "from": "Giraffe",
    "to": "Bonobo"
  },
  {
    "from": "Giraffe",
    "to": "Heron"
  },
  {
    "from": "Mosquito",
    "to": "Donkey"
  },
  {
    "from": "Mosquito",
    "to": "Emu"
  },
  {
    "from": "Mosquito",
    "to": "Crane Fly"
  },
  {
    "from": "Mosquito",
    "to": "Starfish"
  },
  {
    "from": "Mosquito",
    "to": "Minnow"
  },
  {
    "from": "Mosquito",
    "to": "Guan"
  },
  {
    "from": "Anteater",
    "to": "Fowl"
  },
  {
    "from": "Anteater",
    "to": "Alligator"
  },
  {
    "from": "Anteater",
    "to": "Raven"
  },
  {
    "from": "Anteater",
    "to": "Bee"
  },
  {
    "from": "Anteater",
    "to": "Leopard"
  },
  {
    "from": "Anteater",
    "to": "Swan"
  },
  {
    "from": "Swift",
    "to": "Fruit Bat"
  },
  {
    "from": "Swift",
    "to": "Snail"
  },
  {
    "from": "Swift",
    "to": "Bee"
  },
  {
    "from": "Swift",
    "to": "Rhinoceros"
  },
  {
    "from": "Swift",
    "to": "Mosquito"
  },
  {
    "from": "Swift",
    "to": "Mite"
  },
  {
    "from": "Anaconda",
    "to": "Reindeer"
  },
  {
    "from": "Anaconda",
    "to": "Fowl"
  },
  {
    "from": "Anaconda",
    "to": "Carp"
  },
  {
    "from": "Anaconda",
    "to": "Fruit Bat"
  },
  {
    "from": "Anaconda",
    "to": "Anteater"
  },
  {
    "from": "Anaconda",
    "to": "Jellyfish"
  },
  {
    "from": "Angelfish",
    "to": "Armadillo"
  },
  {
    "from": "Angelfish",
    "to": "Lark"
  },
  {
    "from": "Angelfish",
    "to": "Carp"
  },
  {
    "from": "Angelfish",
    "to": "Starfish"
  },
  {
    "from": "Angelfish",
    "to": "Salmon"
  },
  {
    "from": "Porcupine",
    "to": "Fowl"
  },
  {
    "from": "Porcupine",
    "to": "Blue Whale"
  },
  {
    "from": "Porcupine",
    "to": "Lark"
  },
  {
    "from": "Porcupine",
    "to": "Fruit Bat"
  },
  {
    "from": "Porcupine",
    "to": "Leopard"
  },
  {
    "from": "Porcupine",
    "to": "Reptile"
  },
  {
    "from": "Panda",
    "to": "Armadillo"
  },
  {
    "from": "Panda",
    "to": "Domestic Canary"
  },
  {
    "from": "Panda",
    "to": "Fowl"
  },
  {
    "from": "Panda",
    "to": "Starfish"
  },
  {
    "from": "Panda",
    "to": "Ant"
  },
  {
    "from": "Minnow",
    "to": "Penguin"
  },
  {
    "from": "Minnow",
    "to": "Carp"
  },
  {
    "from": "Minnow",
    "to": "Buffalo"
  },
  {
    "from": "Minnow",
    "to": "Alligator"
  },
  {
    "from": "Minnow",
    "to": "Domestic Goose"
  },
  {
    "from": "Minnow",
    "to": "Anaconda"
  },
  {
    "from": "Falcon",
    "to": "Blue Whale"
  },
  {
    "from": "Falcon",
    "to": "Starfish"
  },
  {
    "from": "Falcon",
    "to": "Crane Fly"
  },
  {
    "from": "Falcon",
    "to": "Armadillo"
  },
  {
    "from": "Falcon",
    "to": "Sheep"
  },
  {
    "from": "Falcon",
    "to": "Anglerfish"
  },
  {
    "from": "Dung Beetle",
    "to": "Rhinoceros"
  },
  {
    "from": "Dung Beetle",
    "to": "Buffalo"
  },
  {
    "from": "Dung Beetle",
    "to": "Snail"
  },
  {
    "from": "Dung Beetle",
    "to": "Fowl"
  },
  {
    "from": "Dung Beetle",
    "to": "Ocelot"
  },
  {
    "from": "Dung Beetle",
    "to": "Turtle"
  }
]